{
  "_fv": 79,
  "_type": "tool",
  "definition": {
    "toolType": "Pickaxe",
    "renderType": 0,
    "blockingRenderType": 0,
    "texture": "ancientpickaxe",
    "customModelName": "Normal",
    "blockingModelName": "Normal blocking",
    "name": "Anchient Pickaxe",
    "specialInformation": {
      "fixedValue": []
    },
    "creativeTabs": [
      {
        "value": "CUSTOM:AncientTools"
      }
    ],
    "efficiency": 10.5,
    "attackSpeed": 1.0,
    "enchantability": 16,
    "damageVsEntity": 7.7,
    "usageCount": 4062,
    "repairItems": [
      {
        "value": "CUSTOM:AncientIngot"
      }
    ],
    "immuneToFire": true,
    "blockDropsTier": "NETHERITE",
    "blocksAffected": [],
    "stayInGridWhenCrafting": true,
    "damageOnCrafting": true
  }
}